diploshic/__init__.py
diploshic/fvTools.py
diploshic/generateSimLaunchScript.py
diploshic/makeFeatureVecsForChrArmFromVcfDiploid.py
diploshic/makeFeatureVecsForChrArmFromVcf_ogSHIC.py
diploshic/makeFeatureVecsForSingleMsDiploid.py
diploshic/makeFeatureVecsForSingleMs_ogSHIC.py
diploshic/makeTrainingSets.py
diploshic/msTools.py
diploshic/setup.py
diploshictest-0.2.data/scripts/diploSHIC
diploshictest-0.2.dist-info/LICENCE
diploshictest-0.2.dist-info/METADATA
diploshictest-0.2.dist-info/WHEEL
diploshictest-0.2.dist-info/top_level.txt
diploshictest-0.2.dist-info/RECORD
