Metadata-Version: 2.1
Name: diploshictest
Version: 0.2
Summary: DiploS/HIC
Home-page: https://github.com/jgallowa07/diploSHIC
Author: Andrew Kern
Author-email: 
License: MIT
Platform: UNKNOWN
Requires-Dist: numpy
Requires-Dist: scipy
Requires-Dist: pandas
Requires-Dist: scikit-allel
Requires-Dist: scikit-learn
Requires-Dist: tensorflow
Requires-Dist: keras
Provides-Extra: dev
